django_middleware_fileuploadvalidation/File.py
django_middleware_fileuploadvalidation/FileUploadHandler.py
django_middleware_fileuploadvalidation/__init__.py
django_middleware_fileuploadvalidation/data/whitelists.py
django_middleware_fileuploadvalidation/decorators.py
django_middleware_fileuploadvalidation/middleware.py
django_middleware_fileuploadvalidation/modules/converter.py
django_middleware_fileuploadvalidation/modules/evaluator.py
django_middleware_fileuploadvalidation/modules/reporter.py
django_middleware_fileuploadvalidation/modules/sanitization/application.py
django_middleware_fileuploadvalidation/modules/sanitization/basic.py
django_middleware_fileuploadvalidation/modules/sanitization/image.py
django_middleware_fileuploadvalidation/modules/sanitization/sanitizer.py
django_middleware_fileuploadvalidation/modules/validation/basic.py
django_middleware_fileuploadvalidation/modules/validation/image.py
django_middleware_fileuploadvalidation/modules/validation/quicksand.py
django_middleware_fileuploadvalidation/modules/validation/validator.py
django_middleware_fileuploadvalidation/modules/validation/video.py
django_middleware_fileuploadvalidation/vendor/yara/.gitkeep
django_middleware_fileuploadvalidation/vendor/yara/052618-drupalsite.yar
django_middleware_fileuploadvalidation/vendor/yara/052918_case109.yar
django_middleware_fileuploadvalidation/vendor/yara/1-shell-093018.yar
django_middleware_fileuploadvalidation/vendor/yara/105mail-recon.yar
django_middleware_fileuploadvalidation/vendor/yara/404-2-shell-032118.yar
django_middleware_fileuploadvalidation/vendor/yara/404-shell-032118.yar
django_middleware_fileuploadvalidation/vendor/yara/4700up-jpg.yar
django_middleware_fileuploadvalidation/vendor/yara/620adjs_101118.yar
django_middleware_fileuploadvalidation/vendor/yara/BabaYaga.yar
django_middleware_fileuploadvalidation/vendor/yara/CPR4616Webshell.yar
django_middleware_fileuploadvalidation/vendor/yara/FOPO.yar
django_middleware_fileuploadvalidation-1.1.0.dist-info/LICENSE
django_middleware_fileuploadvalidation-1.1.0.dist-info/METADATA
django_middleware_fileuploadvalidation-1.1.0.dist-info/WHEEL
django_middleware_fileuploadvalidation-1.1.0.dist-info/RECORD
