Metadata-Version: 2.1
Name: django-middleware-fileuploadvalidation
Version: 1.1.0
Summary: A Django middleware to validate user file uploads and detect malicious content.
Author: IV1T3
Author-email: alexander.groddeck@uni-hamburg.de
Requires-Python: >=3.11,<4.0
Classifier: Programming Language :: Python :: 3
Classifier: Programming Language :: Python :: 3.11
Classifier: Programming Language :: Python :: 3.12
Requires-Dist: clamd (>=1.0.2,<2.0.0)
Requires-Dist: django
Requires-Dist: django-stubs[compatible-mypy] (>=4.2.7,<5.0.0)
Requires-Dist: exifread (>=3.0.0,<4.0.0)
Requires-Dist: oletools (>=0.60.1,<0.61.0)
Requires-Dist: pdfid (>=1.1.3,<2.0.0)
Requires-Dist: pillow (>=10.2.0,<11.0.0)
Requires-Dist: python-magic (>=0.4.27,<0.5.0)
Requires-Dist: quicksand (>=2.0.13,<3.0.0)
Requires-Dist: setuptools (>=69.0.3,<70.0.0)
Requires-Dist: types-exifread (>=3.0.0.20240106,<4.0.0.0)
Requires-Dist: yara-python (==4.2.3)
